plotly_presentation/__init__.py
plotly_presentation/examples.py
plotly_presentation/_core/__init__.py
plotly_presentation/_core/analysis.py
plotly_presentation/_core/callouts.py
plotly_presentation/_core/options.py
plotly_presentation/_core/plotter.py
plotly_presentation/_core/style.py
plotly_presentation/_core/_defaults/callout_settings_config.yaml
plotly_presentation/_core/_defaults/colors_config.yaml
plotly_presentation/_core/_defaults/layout_config.yaml
plotly_presentation/_core/_defaults/options_config.yaml
plotly_presentation/_core/analysis_helper/__init__.py
plotly_presentation/_core/analysis_helper/comparison.py
plotly_presentation/_core/analysis_helper/price_volume.py
plotly_presentation/_core/analysis_helper/utils.py
plotly_presentation/_core/colors/__init__.py
plotly_presentation/_core/colors/_colors.py
plotly_presentation/_core/colors/diverging.py
plotly_presentation/_core/colors/sequential.py
plotly_presentation/_core/colors/utils.py
plotly_presentation/_core/utils/__init__.py
plotly_presentation/_core/utils/color_helper.py
plotly_presentation/_core/utils/dict_funcs.py
plotly_presentation/_core/utils/root_searcher.py
plotly_presentation-0.11.3.dist-info/METADATA
plotly_presentation-0.11.3.dist-info/WHEEL
plotly_presentation-0.11.3.dist-info/licenses/LICENSE
plotly_presentation-0.11.3.dist-info/RECORD
